MianxiangJisuanjiShijueDeShenduXuexiChuyiFix1/README.md
MianxiangJisuanjiShijueDeShenduXuexiChuyiFix1/__init__.py
MianxiangJisuanjiShijueDeShenduXuexiChuyiFix1/__main__.py
MianxiangJisuanjiShijueDeShenduXuexiChuyiFix1/file.epub
MianxiangJisuanjiShijueDeShenduXuexiChuyiFix1/index.html
MianxiangJisuanjiShijueDeShenduXuexiChuyiFix1/css/__init__.py
MianxiangJisuanjiShijueDeShenduXuexiChuyiFix1/css/annotations.css
MianxiangJisuanjiShijueDeShenduXuexiChuyiFix1/css/main.css
MianxiangJisuanjiShijueDeShenduXuexiChuyiFix1/css/normalize.css
MianxiangJisuanjiShijueDeShenduXuexiChuyiFix1/css/popup.css
MianxiangJisuanjiShijueDeShenduXuexiChuyiFix1/font/__init__.py
MianxiangJisuanjiShijueDeShenduXuexiChuyiFix1/font/fontello.eot
MianxiangJisuanjiShijueDeShenduXuexiChuyiFix1/font/fontello.svg
MianxiangJisuanjiShijueDeShenduXuexiChuyiFix1/font/fontello.ttf
MianxiangJisuanjiShijueDeShenduXuexiChuyiFix1/font/fontello.woff
MianxiangJisuanjiShijueDeShenduXuexiChuyiFix1/img/__init__.py
MianxiangJisuanjiShijueDeShenduXuexiChuyiFix1/img/annotator-glyph-sprite.png
MianxiangJisuanjiShijueDeShenduXuexiChuyiFix1/img/annotator-icon-sprite.png
MianxiangJisuanjiShijueDeShenduXuexiChuyiFix1/img/apple-touch-icon.png
MianxiangJisuanjiShijueDeShenduXuexiChuyiFix1/img/cancelfullscreen.png
MianxiangJisuanjiShijueDeShenduXuexiChuyiFix1/img/close.png
MianxiangJisuanjiShijueDeShenduXuexiChuyiFix1/img/fullscreen.png
MianxiangJisuanjiShijueDeShenduXuexiChuyiFix1/img/loader.gif
MianxiangJisuanjiShijueDeShenduXuexiChuyiFix1/img/menu-icon.png
MianxiangJisuanjiShijueDeShenduXuexiChuyiFix1/img/save.png
MianxiangJisuanjiShijueDeShenduXuexiChuyiFix1/img/saved.png
MianxiangJisuanjiShijueDeShenduXuexiChuyiFix1/img/settings-s.png
MianxiangJisuanjiShijueDeShenduXuexiChuyiFix1/img/settings.png
MianxiangJisuanjiShijueDeShenduXuexiChuyiFix1/img/star.png
MianxiangJisuanjiShijueDeShenduXuexiChuyiFix1/js/__init__.py
MianxiangJisuanjiShijueDeShenduXuexiChuyiFix1/js/epub.js
mianxiang_jisuanji_shijue_de_shendu_xuexi_chuyi_fix1-2025.3.24.0.dist-info/METADATA
mianxiang_jisuanji_shijue_de_shendu_xuexi_chuyi_fix1-2025.3.24.0.dist-info/WHEEL
mianxiang_jisuanji_shijue_de_shendu_xuexi_chuyi_fix1-2025.3.24.0.dist-info/entry_points.txt
mianxiang_jisuanji_shijue_de_shendu_xuexi_chuyi_fix1-2025.3.24.0.dist-info/top_level.txt
mianxiang_jisuanji_shijue_de_shendu_xuexi_chuyi_fix1-2025.3.24.0.dist-info/RECORD
